<?xml version="1.0"?>
<!DOCTYPE hibernate-mapping PUBLIC "-//Hibernate/Hibernate Mapping DTD 3.0//EN"
"http://hibernate.sourceforge.net/hibernate-mapping-3.0.dtd">
<hibernate-mapping>
	<class name="org.java.mql.models.Etudiant" table="ETUDIANT">
		<id name="id" type="long" column="ETUDIANT_ID">
			<generator class="native" />
		</id>
		<property name="nom" column="NOM" type="string" />
		<property name="prenom" column="PRENOM" type="string" />
		<property name="email" column="EMAIL" type="string" />
		<property name="phone" column="PHONE" type="string" />
	</class>
</hibernate-mapping>